translate_projects_django/__init__.py
translate_projects_django/api_utils.py
translate_projects_django/apps.py
translate_projects_django/hash_utils.py
translate_projects_django/manage_translations.py
translate_projects_django/translation_utils.py
translate_projects_django/management/__init__.py
translate_projects_django/management/commands/__init__.py
translate_projects_django/management/commands/translate.py
translate_projects_django/migrations/__init__.py
translate_projects_django-0.0.6.dist-info/METADATA
translate_projects_django-0.0.6.dist-info/WHEEL
translate_projects_django-0.0.6.dist-info/top_level.txt
translate_projects_django-0.0.6.dist-info/RECORD
