Metadata-Version: 2.1
Name: translate-projects-django
Version: 0.0.6
Summary: Translate your Django projects easily
Home-page: https://github.com/translate-projects/translate-projects-django
Author: Neider Ruiz
Author-email: contact@neiderruiz.com
License: MIT
Platform: UNKNOWN
Classifier: Development Status :: 3 - Alpha
Classifier: Intended Audience :: Developers
Classifier: License :: OSI Approved :: MIT License
Classifier: Programming Language :: Python :: 3
Classifier: Programming Language :: Python :: 3.7
Classifier: Programming Language :: Python :: 3.8
Classifier: Programming Language :: Python :: 3.9
Classifier: Programming Language :: Python :: 3.10
Classifier: Framework :: Django
Classifier: Framework :: Django :: 3.0
Classifier: Framework :: Django :: 3.1
Classifier: Framework :: Django :: 3.2
Requires-Python: >=3.7
Requires-Dist: Django>=3.0
Requires-Dist: polib>=1.2.0
Requires-Dist: requests<3.0,>=2.27.1
